pytest_platform_markers.py
pytest_platform_markers-1.0.0.dist-info/LICENSE
pytest_platform_markers-1.0.0.dist-info/METADATA
pytest_platform_markers-1.0.0.dist-info/WHEEL
pytest_platform_markers-1.0.0.dist-info/entry_points.txt
pytest_platform_markers-1.0.0.dist-info/top_level.txt
pytest_platform_markers-1.0.0.dist-info/RECORD
