Metadata-Version: 2.1
Name: pytest-platform-markers
Version: 1.0.0
Summary: Markers for pytest to skip tests on specific platforms
Home-page: https://github.com/The-Compiler/pytest-platform-markers
Author: Florian Bruhin
Author-email: me@the-compiler.org
Maintainer: Florian Bruhin
Maintainer-email: me@the-compiler.org
License: MIT
Platform: UNKNOWN
Classifier: Development Status :: 4 - Beta
Classifier: Intended Audience :: Developers
Classifier: Topic :: Software Development :: Testing
Classifier: Programming Language :: Python
Classifier: Programming Language :: Python :: 2
Classifier: Programming Language :: Python :: 2.7
Classifier: Programming Language :: Python :: 3
Classifier: Programming Language :: Python :: 3.5
Classifier: Programming Language :: Python :: 3.6
Classifier: Programming Language :: Python :: 3.7
Classifier: Programming Language :: Python :: Implementation :: CPython
Classifier: Programming Language :: Python :: Implementation :: PyPy
Classifier: Operating System :: OS Independent
Classifier: License :: OSI Approved :: MIT License
Requires-Dist: pytest (>=3.6.0)
